django_simple_poll-0.2.3.dist-info/DESCRIPTION.rst
django_simple_poll-0.2.3.dist-info/METADATA
django_simple_poll-0.2.3.dist-info/RECORD
django_simple_poll-0.2.3.dist-info/WHEEL
django_simple_poll-0.2.3.dist-info/metadata.json
django_simple_poll-0.2.3.dist-info/top_level.txt
poll/__init__.py
poll/admin.py
poll/models.py
poll/tests.py
poll/urls.py
poll/utils.py
poll/views.py
poll/locale/.DS_Store
poll/locale/cs/LC_MESSAGES/django.mo
poll/locale/cs/LC_MESSAGES/django.po
poll/locale/es_AR/LC_MESSAGES/django.mo
poll/locale/es_AR/LC_MESSAGES/django.po
poll/locale/ru/LC_MESSAGES/django.mo
poll/locale/ru/LC_MESSAGES/django.po
poll/migrations/0001_initial.py
poll/migrations/__init__.py
poll/templates/poll/base.html
poll/templates/poll/poll.html
poll/templates/poll/result.html
poll/templatetags/__init__.py
poll/templatetags/poll_tags.py
